[
  {
    "id": 1,
    "nombre": "María García",
    "email": "maria@email.com",
    "mensaje": "Excelente servicio y atención. Mi Cocker Spaniel está muy feliz.",
    "calificacion": 5,
    "fecha": "2025-01-01T12:00:00.000Z",
    "aprobado": true
  },
  {
    "id": 2,
    "nombre": "Carlos Rodríguez",
    "email": "carlos@email.com",
    "mensaje": "Profesionales muy dedicados. Recomiendo totalmente.",
    "calificacion": 5,
    "fecha": "2025-01-15T14:30:00.000Z",
    "aprobado": true
  },
  {
    "id": 3,
    "nombre": "Ana López",
    "email": "ana@email.com",
    "mensaje": "Mi Schnauzer recibió el mejor cuidado posible.",
    "calificacion": 5,
    "fecha": "2025-02-01T10:15:00.000Z",
    "aprobado": true
  }
]